traildb/__init__.py
traildb/db_import.py
traildb/endpoints.ini
traildb-0.1.2.dist-info/METADATA
traildb-0.1.2.dist-info/WHEEL
traildb-0.1.2.dist-info/top_level.txt
traildb-0.1.2.dist-info/RECORD
