Metadata-Version: 2.1
Name: traildb
Version: 0.1.2
Summary: The Central Information Source For AI Development
Home-page: https://www.trail-ml.com/?utm_source=pypi&utm_medium=pypi&utm_campaign=pypi
Author: NP
Author-email: nikolaus@trail-ml.com
License: MIT
Classifier: Intended Audience :: Developers
Classifier: License :: OSI Approved :: MIT License
Classifier: Programming Language :: Python
Classifier: Programming Language :: Python :: 3
Classifier: Programming Language :: Python :: 3.6
Classifier: Programming Language :: Python :: 3.7
Classifier: Programming Language :: Python :: 3.8
Classifier: Programming Language :: Python :: 3.9
Classifier: Programming Language :: Python :: 3.10
Classifier: Operating System :: OS Independent
Requires-Dist: mlflow
Requires-Dist: aiohttp
Requires-Dist: gql
Requires-Dist: pyrebase4
